{
  "indexes": [
    {
      "collectionGroup": "scheduledAlerts",
      "queryScope": "COLLECTION",
      "fields": [
        { "fieldPath": "status", "order": "ASCENDING" },
        { "fieldPath": "scheduledTime", "order": "ASCENDING" }
      ]
    },
    {
      "collectionGroup": "scheduledAlerts",
      "queryScope": "COLLECTION",
      "fields": [
        { "fieldPath": "deleted", "order": "ASCENDING" },
        { "fieldPath": "status", "order": "ASCENDING" },
        { "fieldPath": "notificationSent", "order": "ASCENDING" },
        { "fieldPath": "scheduledTime", "order": "ASCENDING" }
      ]
    },
    {
      "collectionGroup": "scheduledAlerts",
      "queryScope": "COLLECTION",
      "fields": [
        { "fieldPath": "status", "order": "ASCENDING" },
        { "fieldPath": "notificationSent", "order": "ASCENDING" },
        { "fieldPath": "deleted", "order": "ASCENDING" },
        { "fieldPath": "instanceState", "order": "ASCENDING" },
        { "fieldPath": "scheduledTime", "order": "ASCENDING" }
      ]
    },
    {
      "collectionGroup": "scheduledAlerts",
      "queryScope": "COLLECTION",
      "fields": [
        { "fieldPath": "userId", "order": "ASCENDING" },
        { "fieldPath": "region", "order": "ASCENDING" },
        { "fieldPath": "type", "order": "ASCENDING" }
      ]
    },
    {
      "collectionGroup": "scheduledAlerts",
      "queryScope": "COLLECTION",
      "fields": [
        { "fieldPath": "instanceId", "order": "ASCENDING" },
        { "fieldPath": "status", "order": "ASCENDING" },
        { "fieldPath": "deleted", "order": "ASCENDING" }
      ]
    },
    {
      "collectionGroup": "scheduledAlerts",
      "queryScope": "COLLECTION",
      "fields": [
        { "fieldPath": "type", "order": "ASCENDING" },
        { "fieldPath": "status", "order": "ASCENDING" }
      ]
    },
    {
      "collectionGroup": "scheduledAlerts",
      "queryScope": "COLLECTION",
      "fields": [
        { "fieldPath": "region", "order": "ASCENDING" },
        { "fieldPath": "status", "order": "ASCENDING" },
        { "fieldPath": "appTerminated", "order": "ASCENDING" }
      ]
    },
    {
      "collectionGroup": "notificationHistory",
      "queryScope": "COLLECTION",
      "fields": [
        { "fieldPath": "region", "order": "ASCENDING" },
        { "fieldPath": "timestamp", "order": "DESCENDING" }
      ]
    },
    {
      "collectionGroup": "scheduledAlerts",
      "queryScope": "COLLECTION",
      "fields": [
        { "fieldPath": "deleted", "order": "ASCENDING" },
        { "fieldPath": "notificationSent", "order": "ASCENDING" },
        { "fieldPath": "status", "order": "ASCENDING" },
        { "fieldPath": "type", "order": "ASCENDING" },
        { "fieldPath": "scheduledTime", "order": "ASCENDING" }
      ]
    },
    {
      "collectionGroup": "scheduledAlerts",
      "queryScope": "COLLECTION",
      "fields": [
        { "fieldPath": "status", "order": "ASCENDING" },
        { "fieldPath": "notificationSent", "order": "ASCENDING" },
        { "fieldPath": "deleted", "order": "ASCENDING" },
        { "fieldPath": "type", "order": "ASCENDING" },
        { "fieldPath": "scheduledTime", "order": "ASCENDING" }
      ]
    },
    {
      "collectionGroup": "scheduledAlerts",
      "queryScope": "COLLECTION",
      "fields": [
        { "fieldPath": "instanceState", "order": "ASCENDING" },
        { "fieldPath": "createdAt", "order": "ASCENDING" },
        { "fieldPath": "__name__", "order": "ASCENDING" }
      ]
    },
    {
      "collectionGroup": "scheduledAlerts",
      "queryScope": "COLLECTION",
      "fields": [
        { "fieldPath": "instanceState", "order": "ASCENDING" },
        { "fieldPath": "createdAt", "order": "ASCENDING" }
      ]
    },
    {
      "collectionGroup": "scheduledAlerts",
      "queryScope": "COLLECTION",
      "fields": [
        { "fieldPath": "instanceState", "arrayConfig": "CONTAINS" },
        { "fieldPath": "createdAt", "order": "ASCENDING" }
      ]
    },
    {
      "collectionGroup": "scheduledAlerts",
      "queryScope": "COLLECTION",
      "fields": [
        { "fieldPath": "instanceState", "arrayConfig": "CONTAINS" }
      ]
    },
    {
      "collectionGroup": "scheduledAlerts",
      "queryScope": "COLLECTION",
      "fields": [
        { "fieldPath": "createdAt", "order": "ASCENDING" }
      ]
    },
    {
      "collectionGroup": "scheduledAlerts",
      "queryScope": "COLLECTION",
      "fields": [
        { "fieldPath": "deleted", "order": "ASCENDING" },
        { "fieldPath": "status", "order": "ASCENDING" },
        { "fieldPath": "notificationSent", "order": "ASCENDING" },
        { "fieldPath": "type", "order": "ASCENDING" },
        { "fieldPath": "scheduledTime", "order": "ASCENDING" },
        { "fieldPath": "__name__", "order": "ASCENDING" }
      ]
    },
    {
      "collectionGroup": "scheduledAlerts",
      "queryScope": "COLLECTION",
      "fields": [
        { "fieldPath": "status", "order": "ASCENDING" },
        { "fieldPath": "notificationSent", "order": "ASCENDING" },
        { "fieldPath": "scheduledTime", "order": "ASCENDING" }
      ]
    },
    {
      "collectionGroup": "scheduledAlerts",
      "queryScope": "COLLECTION",
      "fields": [
        { "fieldPath": "deleted", "order": "ASCENDING" },
        { "fieldPath": "status", "order": "ASCENDING" },
        { "fieldPath": "type", "order": "ASCENDING" },
        { "fieldPath": "scheduledTime", "order": "ASCENDING" }
      ]
    },
    {
      "collectionGroup": "scheduledAlerts",
      "queryScope": "COLLECTION",
      "fields": [
        { "fieldPath": "deleted", "order": "ASCENDING" },
        { "fieldPath": "notificationSent", "order": "ASCENDING" },
        { "fieldPath": "type", "order": "ASCENDING" },
        { "fieldPath": "scheduledTime", "order": "ASCENDING" }
      ]
    },
    {
      "collectionGroup": "scheduledAlerts",
      "queryScope": "COLLECTION",
      "fields": [
        { "fieldPath": "deleted", "order": "ASCENDING" },
        { "fieldPath": "notificationSent", "order": "ASCENDING" },
        { "fieldPath": "type", "order": "ASCENDING" },
        { "fieldPath": "scheduledTime", "order": "ASCENDING" }
      ]
    },
    {
      "collectionGroup": "notificationHistory",
      "queryScope": "COLLECTION",
      "fields": [
        { "fieldPath": "timestamp", "order": "ASCENDING" }
      ]
    },
    {
      "collectionGroup": "failedNotifications",
      "queryScope": "COLLECTION",
      "fields": [
        { "fieldPath": "timestamp", "order": "ASCENDING" }
      ]
    },
    {
      "collectionGroup": "scheduledAlerts",
      "queryScope": "COLLECTION",
      "fields": [
        { "fieldPath": "status", "order": "ASCENDING" },
        { "fieldPath": "createdAt", "order": "ASCENDING" }
      ]
    }
  ],
  "fieldOverrides": []
} 